crowd_eval/__init__.py
crowd_eval/checkpoint_evaluation/__init__.py
crowd_eval/checkpoint_evaluation/checkpoint_evaluator.py
crowd_eval/checkpoint_evaluation/image_checkpoint_evaluator.py
crowd_eval/logger/__init__.py
crowd_eval/logger/ordered_wandb_logger.py
crowd_eval-0.3.0.dist-info/METADATA
crowd_eval-0.3.0.dist-info/WHEEL
crowd_eval-0.3.0.dist-info/RECORD
