Metadata-Version: 2.4
Name: crowd-eval
Version: 0.3.0
Summary: Human evaluation tools for AI models and datasets
Requires-Python: >=3.9
Requires-Dist: rapidata>=2.27.0
Requires-Dist: wandb>=0.20.0
